aaltopoiju/__init__.py
aaltopoiju-0.0.3.dist-info/DESCRIPTION.rst
aaltopoiju-0.0.3.dist-info/METADATA
aaltopoiju-0.0.3.dist-info/metadata.json
aaltopoiju-0.0.3.dist-info/RECORD
aaltopoiju-0.0.3.dist-info/top_level.txt
aaltopoiju-0.0.3.dist-info/WHEEL
fmiweather/__init__.py
